tests/__init__.py
tests/fancywallet_get_price_test.py
PhilSfancywallet-0.1.0.dist-info/METADATA
PhilSfancywallet-0.1.0.dist-info/WHEEL
PhilSfancywallet-0.1.0.dist-info/entry_points.txt
PhilSfancywallet-0.1.0.dist-info/top_level.txt
PhilSfancywallet-0.1.0.dist-info/RECORD
