Metadata-Version: 2.1
Name: PhilSfancywallet
Version: 0.1.0
Requires-Dist: click
Requires-Dist: requests
